bindy/__init__.py
bindy/bindy.py
bindy/lowlevel.py
bindy/debian/libbindy.so
bindy/win32/bindy.dll
bindy/win64/bindy.dll
bindy-2.0.1.dist-info/METADATA
bindy-2.0.1.dist-info/WHEEL
bindy-2.0.1.dist-info/entry_points.txt
bindy-2.0.1.dist-info/license_files/LICENSE
bindy-2.0.1.dist-info/RECORD
