Metadata-Version: 2.1
Name: bindy
Version: 2.0.1
Summary: A lightweight cross-platform framework for cloud service
Project-URL: Homepage, https://github.com/EPC-MSU/Bindy
Author-email: EPC MSU <info@physlab.ru>
License: The MIT License (MIT)
Classifier: License :: OSI Approved :: MIT License
Classifier: Operating System :: OS Independent
Classifier: Programming Language :: Python :: 3
Requires-Python: >=3.6
